rtms_sdk_module/SiemensDevice.py
rtms_sdk_module/__init__.py
rtms_sdk_module/Const/SiemensCrnConst.py
rtms_sdk_module/Const/__init__.py
rtms_sdk_module/Exception/CRNCommError.py
rtms_sdk_module/Exception/CRNTaskError.py
rtms_sdk_module/Exception/CRNWarningException.py
rtms_sdk_module/Exception/CRNWriteDataError.py
rtms_sdk_module/Exception/__init__.py
rtms_sdk_module/Service/MySnap7.py
rtms_sdk_module/Service/__init__.py
rtms_sdk-0.1.16.dist-info/METADATA
rtms_sdk-0.1.16.dist-info/WHEEL
rtms_sdk-0.1.16.dist-info/top_level.txt
rtms_sdk-0.1.16.dist-info/RECORD
