Metadata-Version: 2.1
Name: rtms-sdk
Version: 0.1.16
Summary: plc connect
Home-page: UNKNOWN
Author: Bao Yun
Author-email: 305713412@qq.com
License: UNKNOWN
Platform: UNKNOWN
